[{"name":"Мария","surname":"Усс","lastname":"Павловна","birthday":"2000-03-01T00:00:00.000Z","studyStart":"2019-08-31T21:00:00.000Z","faculty":"Информатика","id":"1713783385606","updatedAt":"2024-04-22T10:56:25.606Z","createdAt":"2024-04-22T10:56:25.606Z"},{"name":"Марина","surname":"Абрамович","lastname":"Геннадьевна","birthday":"2001-03-03T00:00:00.000Z","studyStart":"2020-08-31T21:00:00.000Z","faculty":"Информатика","id":"1713783477643","updatedAt":"2024-04-22T10:57:57.643Z","createdAt":"2024-04-22T10:57:57.643Z"},{"name":"Екатерина","surname":"Ломако","lastname":"Александровна","birthday":"1999-06-09T00:00:00.000Z","studyStart":"2015-08-31T21:00:00.000Z","faculty":"Маркетинг","id":"1714672729291","updatedAt":"2024-05-02T17:58:49.291Z","createdAt":"2024-05-02T17:58:49.291Z"},{"name":"Анастасия","surname":"Ломако","lastname":"Александровна","birthday":"1999-06-18T00:00:00.000Z","studyStart":"2017-08-31T21:00:00.000Z","faculty":"Коммерция","id":"1714673285067","updatedAt":"2024-05-02T18:08:05.068Z","createdAt":"2024-05-02T18:08:05.068Z"},{"name":"Виктория","surname":"Карась","lastname":"Александровна","birthday":"1996-05-29T00:00:00.000Z","studyStart":"2024-08-31T21:00:00.000Z","faculty":"Коммерция","id":"1714673494616","updatedAt":"2024-05-02T18:11:34.616Z","createdAt":"2024-05-02T18:11:34.616Z"}]